optimyzer_api_client/__init__.py
optimyzer_api_client/api_connection.py
optimyzer_api_client/client.py
optimyzer_api_client/machine.py
optimyzer_api_client/optimization.py
optimyzer_api_client/secret_loader.py
optimyzer_api_client-0.5.1.dist-info/LICENSE
optimyzer_api_client-0.5.1.dist-info/METADATA
optimyzer_api_client-0.5.1.dist-info/WHEEL
optimyzer_api_client-0.5.1.dist-info/top_level.txt
optimyzer_api_client-0.5.1.dist-info/RECORD
