Metadata-Version: 2.1
Name: optimyzer-api-client
Version: 0.5.1
Summary: An API Client for Optimyzer
Home-page: https://gitlab.com/gauss-ml-open/optimyzer-api-client
Author: Gauss Machine Learning GmbH
Author-email: info@gauss-ml.com
License: UNKNOWN
Keywords: parameter optimization,machine learning,artificial intelligence,neural networks
Platform: UNKNOWN
Classifier: Development Status :: 4 - Beta
Classifier: Intended Audience :: Developers
Classifier: Intended Audience :: Science/Research
Classifier: Topic :: Scientific/Engineering :: Artificial Intelligence
Classifier: License :: OSI Approved :: BSD License
Classifier: Programming Language :: Python :: 3
Classifier: Programming Language :: Python :: 3.5
Classifier: Programming Language :: Python :: 3.6
Classifier: Programming Language :: Python :: 3.7
Classifier: Programming Language :: Python :: 3.8
Classifier: Programming Language :: Python :: 3 :: Only
Requires-Python: >=3.5, <4
License-File: LICENSE
Requires-Dist: matplotlib
Requires-Dist: numpy
Requires-Dist: requests
Provides-Extra: dev
Requires-Dist: black ; extra == 'dev'
Requires-Dist: flake8 ; extra == 'dev'
Requires-Dist: mypy ; extra == 'dev'
Requires-Dist: pylint ; extra == 'dev'
Requires-Dist: rope ; extra == 'dev'
Provides-Extra: test
Requires-Dist: flaky ; extra == 'test'
Requires-Dist: micro-ci ; extra == 'test'
Requires-Dist: pytest ; extra == 'test'
Requires-Dist: pytest-cov ; extra == 'test'
